petroscope/__init__.py
petroscope/calibrate/__init__.py
petroscope/calibrate/core.py
petroscope/calibrate/run.py
petroscope/examples/calibration.py
petroscope/examples/segm_balancer.py
petroscope/examples/segm_cnn_test.py
petroscope/examples/segm_resunet_inference.py
petroscope/segmentation/__init__.py
petroscope/segmentation/augment.py
petroscope/segmentation/classes.py
petroscope/segmentation/eval.py
petroscope/segmentation/lumenstone.yaml
petroscope/segmentation/metrics.py
petroscope/segmentation/model.py
petroscope/segmentation/utils.py
petroscope/segmentation/vis.py
petroscope/segmentation/balancer/__init__.py
petroscope/segmentation/balancer/balancer.py
petroscope/segmentation/models/__init__.py
petroscope/segmentation/models/color_cluster/model.py
petroscope/segmentation/models/pspnet/__init__.py
petroscope/segmentation/models/pspnet/model.py
petroscope/segmentation/models/pspnet/nn.py
petroscope/segmentation/models/pspnet/train.py
petroscope/segmentation/models/resunet/__init__.py
petroscope/segmentation/models/resunet/model.py
petroscope/segmentation/models/resunet/nn.py
petroscope/segmentation/models/resunet/train.py
petroscope/segmentation/scripts/correct_masks.py
petroscope/segmentation/scripts/print_ds_stats.py
petroscope/segmentation/scripts/resize_ds.py
petroscope/segmentation/scripts/visualize_masks.py
petroscope/utils/__init__.py
petroscope/utils/base.py
petroscope/utils/lazy_imports.py
petroscope/utils/logger.py
petroscope-0.0.11.dist-info/LICENSE
petroscope-0.0.11.dist-info/METADATA
petroscope-0.0.11.dist-info/WHEEL
petroscope-0.0.11.dist-info/top_level.txt
petroscope-0.0.11.dist-info/RECORD
