Metadata-Version: 2.2
Name: petroscope
Version: 0.0.11
Summary: Package containing a set of tools to process and analyze geological microscopic images.
Author-email: Alexander Khvostikov <khvostikov@cs.msu.ru>
Project-URL: Homepage, https://github.com/xubiker/petroscope
Project-URL: Issues, https://github.com/xubiker/petroscope/issues
Classifier: Programming Language :: Python :: 3
Classifier: Intended Audience :: Science/Research
Classifier: License :: OSI Approved :: MIT License
Classifier: Operating System :: OS Independent
Requires-Python: >=3.10
License-File: LICENSE
Requires-Dist: pyyaml
Requires-Dist: numpy<2.0.0,>=1.16
Requires-Dist: pillow
Requires-Dist: matplotlib
Requires-Dist: tqdm
Requires-Dist: scipy
Requires-Dist: loguru
Requires-Dist: prettytable
Requires-Dist: requests
Provides-Extra: extra
Requires-Dist: torch; extra == "extra"
Requires-Dist: torchvision; extra == "extra"
Requires-Dist: kornia; extra == "extra"
Requires-Dist: opencv-python; extra == "extra"
Requires-Dist: hydra-core; extra == "extra"
